clbtope/blast_binaries/linux/blastp
clbtope/blast_binaries/mac/blastp
clbtope/blast_binaries/windows/blastp.exe
clbtope/blast_binaries/windows/nghttp2.dll
clbtope/blast_db/train.pdb
clbtope/blast_db/train.phr
clbtope/blast_db/train.pin
clbtope/blast_db/train.pog
clbtope/blast_db/train.pos
clbtope/blast_db/train.pot
clbtope/blast_db/train.psd
clbtope/blast_db/train.psi
clbtope/blast_db/train.psq
clbtope/blast_db/train.ptf
clbtope/blast_db/train.pto
clbtope/python_scripts/__init__.py
clbtope/python_scripts/clbtope.py
clbtope-1.0.6.dist-info/METADATA
clbtope-1.0.6.dist-info/WHEEL
clbtope-1.0.6.dist-info/entry_points.txt
clbtope-1.0.6.dist-info/top_level.txt
clbtope-1.0.6.dist-info/RECORD
