Metadata-Version: 2.1
Name: clbtope
Version: 1.0.6
Summary: CLBTope:A computational approach had been developed for predicting both types (linear/conformational) of B-cell epitopes.
Home-page: https://github.com/raghavagps/clbtope
Author: Nishant Kumar
Author-email: nishantk@iiitd.ac.in
Requires-Python: >=3.7
Requires-Dist: numpy
Requires-Dist: pandas
Requires-Dist: scikit-learn
Requires-Dist: argparse
Requires-Dist: tqdm
Requires-Dist: onnxruntime
